segmenthee/__init__.py
segmenthee/cart_api.py
segmenthee/config.py
segmenthee/parser_api.py
segmenthee/shop.py
segmentheepy_refl_az-1.1.10.dist-info/METADATA
segmentheepy_refl_az-1.1.10.dist-info/WHEEL
segmentheepy_refl_az-1.1.10.dist-info/top_level.txt
segmentheepy_refl_az-1.1.10.dist-info/RECORD
